{
  "AXE_MODEL_ROLLS": {
    "SCRAPPY": [],
    "COMMON": [],
    "RARE": [],
    "EPIC": [],
    "OMEGA": [],
    "UNIQUE": [
      "the_vault:gear/axe/leviathan",
      "the_vault:gear/axe/zombie_horse"
    ],
    "SPECIAL": [],
    "CHAOTIC": [],
    "MYTHIC": []
  },
  "WAND_MODEL_ROLLS": {
    "SCRAPPY": [],
    "COMMON": [],
    "RARE": [],
    "EPIC": [],
    "OMEGA": [],
    "UNIQUE": [
      "the_vault:gear/wand/chaining_wand",
      "the_vault:gear/wand/baguette"
    ],
    "SPECIAL": [],
    "CHAOTIC": [],
    "MYTHIC": []
  },
  "SWORD_MODEL_ROLLS": {
    "SCRAPPY": [],
    "COMMON": [],
    "RARE": [],
    "EPIC": [],
    "OMEGA": [],
    "UNIQUE": [
      "woldsvaults:gear/sword/lava_chicken_sword",
      "the_vault:gear/sword/everfrost",
      "the_vault:gear/sword/everflame",
      "the_vault:gear/sword/hexblade",
      "the_vault:gear/sword/mineral_greatsword",
      "the_vault:gear/sword/grass_blade",
      "the_vault:gear/sword/aurora_scissors",
      "the_vault:gear/sword/young_kitsune"
    ],
    "SPECIAL": [],
    "CHAOTIC": [],
    "MYTHIC": []
  },
  "ARMOR_MODEL_ROLLS": {
    "SCRAPPY": [],
    "COMMON": [],
    "RARE": [],
    "EPIC": [],
    "OMEGA": [],
    "UNIQUE": [],
    "SPECIAL": [],
    "CHAOTIC": [],
    "MYTHIC": []
  },
  "SHIELD_MODEL_ROLLS": {
    "SCRAPPY": [],
    "COMMON": [],
    "RARE": [],
    "EPIC": [],
    "OMEGA": [],
    "UNIQUE": [],
    "SPECIAL": [],
    "CHAOTIC": [],
    "MYTHIC": []
  },
  "FOCUS_MODEL_ROLLS": {
    "SCRAPPY": [],
    "COMMON": [],
    "RARE": [],
    "EPIC": [],
    "OMEGA": [],
    "UNIQUE": [
      "woldsvaults:gear/focus/chroma_brew"
    ],
    "SPECIAL": [],
    "CHAOTIC": [],
    "MYTHIC": []
  },
  "MAGNETS_MODEL_ROLLS": {
    "SCRAPPY": [],
    "COMMON": [],
    "RARE": [],
    "EPIC": [],
    "OMEGA": [],
    "UNIQUE": [
      "woldsvaults:gear/magnet/aural",
      "the_vault:magnets/heart_magnet",
      "the_vault:magnets/treasure_magnet",
      "the_vault:magnets/bloody_magnet"
    ],
    "SPECIAL": [],
    "CHAOTIC": [],
    "MYTHIC": []
  },
  "TRIDENT_MODEL_ROLLS": {
    "SCRAPPY": [],
    "COMMON": [],
    "RARE": [],
    "EPIC": [],
    "OMEGA": [],
    "UNIQUE": [
      "woldsvaults:gear/trident/ocean_current",
      "woldsvaults:gear/trident/fork"
    ],
    "SPECIAL": [],
    "CHAOTIC": [],
    "MYTHIC": []
  },
  "BATTLESTAFF_MODEL_ROLLS": {
    "SCRAPPY": [],
    "COMMON": [],
    "RARE": [],
    "EPIC": [],
    "OMEGA": [],
    "UNIQUE": [
      "the_vault:gear/battlestaff/bamboo_fightstick"
    ],
    "SPECIAL": [],
    "CHAOTIC": [],
    "MYTHIC": []
  },
  "PLUSHIE_MODEL_ROLLS": {
    "SCRAPPY": [],
    "COMMON": [],
    "RARE": [],
    "EPIC": [],
    "OMEGA": [],
    "UNIQUE": [
      "woldsvaults:gear/plushie/pocket_penguin",
      "the_vault:gear/plushie/witch",
      "the_vault:gear/plushie/safer_spaces"
    ],
    "SPECIAL": [],
    "CHAOTIC": [],
    "MYTHIC": []
  },
  "LOOT_SACK_MODEL_ROLLS": {
    "SCRAPPY": [],
    "COMMON": [],
    "RARE": [],
    "EPIC": [],
    "OMEGA": [],
    "UNIQUE": [],
    "SPECIAL": [],
    "CHAOTIC": [],
    "MYTHIC": []
  },
  "JEWEL_MODEL_ROLLS": {
    "SCRAPPY": [],
    "COMMON": [],
    "RARE": [],
    "EPIC": [],
    "OMEGA": [],
    "UNIQUE": [
      "the_vault:gear/jewel/treasure",
      "the_vault:gear/jewel/stella",
      "the_vault:gear/jewel/treasure"
    ],
    "SPECIAL": [],
    "CHAOTIC": [],
    "MYTHIC": []
  },
  "RANG_MODEL_ROLLS": {
    "SCRAPPY": [],
    "COMMON": [],
    "RARE": [],
    "EPIC": [],
    "OMEGA": [],
    "UNIQUE": [
      "the_vault:gear/rang/trirang"
    ],
    "SPECIAL": [],
    "CHAOTIC": [],
    "MYTHIC": []
  }
}