{
  "parent": "minecraft:recipes/root",
  "rewards": {
    "recipes": [
      "compressium:ancient_copper_block_8_uncraft"
    ]
  },
  "criteria": {
    "has_compressed_ancient_copper_block_x8": {
      "trigger": "minecraft:inventory_changed",
      "conditions": {
        "items": [
          {
            "items": [
              "compressium:ancient_copper_block_8"
            ]
          }
        ]
      }
    },
    "has_the_recipe": {
      "trigger": "minecraft:recipe_unlocked",
      "conditions": {
        "recipe": "compressium:ancient_copper_block_8_uncraft"
      }
    }
  },
  "requirements": [
    [
      "has_compressed_ancient_copper_block_x8",
      "has_the_recipe"
    ]
  ]
}